imaaage/__init__.py
imaaage/adapters.py
imaaage/callback.py
imaaage/evaluate.py
imaaage/log.py
imaaage/path.py
imaaage/performance.py
imaaage/pipeline.py
imaaage/preset.py
imaaage/resolutions.py
imaaage/styles.py
imaaage/metric/__init__.py
imaaage/metric/evaluate.py
imaaage/metric/metric_aesthetic.py
imaaage/metric/metric_clip_score.py
imaaage/metric/metric_fid.py
imaaage/metric/metric_mos.py
imaaage/metric/modules/__init__.py
imaaage/metric/modules/inception.py
imaaage/metric/modules/maniqa.py
imaaage/metric/modules/swin.py
imaaage_ui/__init__.py
imaaage_ui/executor.py
imaaage_ui/html.py
imaaage_ui/webui.py
imaaage-0.0.5.dist-info/METADATA
imaaage-0.0.5.dist-info/WHEEL
imaaage-0.0.5.dist-info/top_level.txt
imaaage-0.0.5.dist-info/RECORD
